srun_swpu/__init__.py
srun_swpu/encryption.py
srun_swpu/exceptions.py
srun_swpu/logger.py
srun_swpu/models.py
srun_swpu/network.py
srun_swpu-0.1.0.dist-info/LICENSE
srun_swpu-0.1.0.dist-info/METADATA
srun_swpu-0.1.0.dist-info/WHEEL
srun_swpu-0.1.0.dist-info/top_level.txt
srun_swpu-0.1.0.dist-info/RECORD
